[{"id":2,"name":"אגרת כסאות","amount":280,"category":"מיסים","type":"fixed","date":null,"created_at":"2026-04-12T17:27:30.874Z"},{"id":3,"name":"אי זי טו פיי (פנסיות)","amount":100,"category":"שכר","type":"fixed","date":null,"created_at":"2026-04-12T17:27:31.063Z"},{"id":4,"name":"איתן עמיחי הדברה","amount":350,"category":"תחזוקה","type":"fixed","date":null,"created_at":"2026-04-12T17:27:31.273Z"},{"id":5,"name":"אם אי אס מחקרים","amount":708,"category":"מקצועי","type":"fixed","date":null,"created_at":"2026-04-12T17:27:31.433Z"},{"id":6,"name":"אפרס מחשבים","amount":100,"category":"תחזוקה","type":"fixed","date":null,"created_at":"2026-04-12T17:27:31.614Z"},{"id":7,"name":"אקו\"ם","amount":180,"category":"מיסים","type":"fixed","date":null,"created_at":"2026-04-12T17:27:31.724Z"},{"id":8,"name":"ארנונה","amount":2350,"category":"מיסים","type":"fixed","date":null,"created_at":"2026-04-12T17:27:31.857Z"},{"id":9,"name":"ארנונה יהודה מכבי","amount":1300,"category":"מיסים","type":"fixed","date":null,"created_at":"2026-04-12T17:27:31.983Z"},{"id":10,"name":"בזק","amount":50,"category":"תקשורת","type":"fixed","date":null,"created_at":"2026-04-12T17:27:32.114Z"},{"id":11,"name":"ביזון","amount":660,"category":"ציוד","type":"fixed","date":null,"created_at":"2026-04-12T17:27:32.243Z"},{"id":12,"name":"ביטוח עסק","amount":500,"category":"ביטוח","type":"fixed","date":null,"created_at":"2026-04-12T17:27:32.376Z"},{"id":13,"name":"ביקום קופות","amount":700,"category":"מקצועי","type":"fixed","date":null,"created_at":"2026-04-12T17:27:32.565Z"},{"id":14,"name":"דירה","amount":2500,"category":"שכירות","type":"fixed","date":null,"created_at":"2026-04-12T17:27:32.684Z"},{"id":15,"name":"דמי כרטיס אשראי","amount":40,"category":"בנק","type":"fixed","date":null,"created_at":"2026-04-12T17:27:32.827Z"},{"id":16,"name":"הוט מובייל","amount":50,"category":"תקשורת","type":"fixed","date":null,"created_at":"2026-04-12T17:27:32.965Z"},{"id":17,"name":"הלוואות","amount":10000,"category":"הלוואות","type":"fixed","date":null,"created_at":"2026-04-12T17:27:33.115Z"},{"id":18,"name":"הפדרציה","amount":153,"category":"מיסים","type":"fixed","date":null,"created_at":"2026-04-12T17:27:33.256Z"},{"id":19,"name":"ווירדוז בע\"מ","amount":815,"category":"מקצועי","type":"fixed","date":null,"created_at":"2026-04-12T17:27:33.385Z"},{"id":20,"name":"וועד בית","amount":120,"category":"שכירות","type":"fixed","date":null,"created_at":"2026-04-12T17:27:33.526Z"},{"id":21,"name":"חיישנים מקרר ומקפיא","amount":150,"category":"תחזוקה","type":"fixed","date":null,"created_at":"2026-04-12T17:27:33.665Z"},{"id":22,"name":"חשמל","amount":4300,"category":"שירותים","type":"fixed","date":null,"created_at":"2026-04-12T17:27:33.795Z"},{"id":23,"name":"חשמל יהודה מכבי","amount":1000,"category":"שירותים","type":"fixed","date":null,"created_at":"2026-04-12T17:27:33.907Z"},{"id":24,"name":"מדיח","amount":1800,"category":"ציוד","type":"fixed","date":null,"created_at":"2026-04-12T17:27:34.016Z"},{"id":25,"name":"מחסן","amount":4100,"category":"שכירות","type":"fixed","date":null,"created_at":"2026-04-12T17:27:34.146Z"},{"id":26,"name":"מים","amount":500,"category":"שירותים","type":"fixed","date":null,"created_at":"2026-04-12T17:27:34.246Z"},{"id":27,"name":"עמלות כרטיסי אשראי","amount":2350,"category":"בנק","type":"fixed","date":null,"created_at":"2026-04-12T17:27:34.346Z"},{"id":28,"name":"עמלות ריביות ופעולות בנק","amount":1600,"category":"בנק","type":"fixed","date":null,"created_at":"2026-04-12T17:27:34.457Z"},{"id":29,"name":"פינוי ביוב","amount":300,"category":"תחזוקה","type":"fixed","date":null,"created_at":"2026-04-12T17:27:34.576Z"},{"id":30,"name":"פרטנר","amount":30,"category":"תקשורת","type":"fixed","date":null,"created_at":"2026-04-12T17:27:34.690Z"},{"id":31,"name":"קוסטה","amount":180,"category":"ציוד","type":"fixed","date":null,"created_at":"2026-04-12T17:27:34.786Z"},{"id":32,"name":"רואה חשבון","amount":2600,"category":"מקצועי","type":"fixed","date":null,"created_at":"2026-04-12T17:27:34.886Z"},{"id":33,"name":"רישוי עסקים","amount":380,"category":"מיסים","type":"fixed","date":null,"created_at":"2026-04-12T17:27:34.987Z"},{"id":34,"name":"שכירות חנות","amount":13000,"category":"שכירות","type":"fixed","date":null,"created_at":"2026-04-12T17:27:35.097Z"}]
